{
    "continuous": [
        {
            "name": "Actuele10mindataKNMIstations",
            "version": "2",
            "topic": "data.actuele10mindataknmistations"
        },

        {
            "name": "precipitation_NL_ensemble_nowcast_5min",
            "version": "1.0",
            "topic": "data.precipitation_nl_ensemble_nowcast_5min"
        },
        {
            "name": "zonneschijnduur_en_straling",
            "version": "2.0",
            "topic": "data.zonneschijnduur_en_straling"
        }
    ],

    "historical": [
        {
            "name": "knmi23_user_friendly_racmo",
            "version": "2.0",
            "topic": "data.knmi23_user_friendly_racmo"
        },
        {
            "name": "hot_air_balloon_derived_winds",
            "version": "2.0",
            "topic": "data.hot_air_balloon_derived_winds"
        }
    ]
}
